{
  "$schema": "http://json-schema.org/draft-04/schema#",
  "description": "An organization category",
  "type": "object",
  "additionalProperties": false,
  "properties": {
    "id": {
      "description": "The unique id of this category",
      "type": [
        "string",
        "null"
      ],
      "pattern": "^[a-fA-F0-9]{8}-[a-fA-F0-9]{4}-[a-fA-F0-9]{4}-[a-fA-F0-9]{4}-[a-fA-F0-9]{12}$"
    },
    "value": {
      "description": "The value of this category",
      "type": "string"
    }
  },
  "required": [
    "value"
  ]
}